{
  "concepts": [
    {
      "title": "Болезни",
      "file": "main.md"
    },
    {
      "title": "Симптомы",
      "file": "symptoms.md"
    },
    {
      "title": "Методы лечения",
      "file": "treatment_methods.md"
    },
    {
      "title": "Предотвращение болезней",
      "file": "prevention.md"
    },
    {
      "title": "Кашель",
      "file": "cough.md"
    },
    {
      "title": "Лихорадка",
      "file": "fever.md"
    },
    {
      "title": "Головная боль",
      "file": "headache.md"
    },
    {
      "title": "Вакцинация",
      "file": "vaccination.md"
    },
    {
      "title": "Противовирусные препараты",
      "file": "antiviral.md"
    },
    {
      "title": "Антибиотики",
      "file": "antibiotics.md"
    },
    {
      "title": "Коронавирус",
      "file": "covid.md"
    },
    {
      "title": "Астма",
      "file": "asthma.md"
    },
    {
      "title": "Одышка",
      "file": "shortness_of_breath.md"
    },
    {
      "title": "Туберкулез",
      "file": "tuberculosis.md"
    },
    {
      "title": "Хронический бронхит",
      "file": "bronchitis.md"
    },
    {
      "title": "Ревматоидный артрит",
      "file": "arthritis.md"
    },
    {
      "title": "Пневмония",
      "file": "pneumonia.md"
    },
    {
      "title": "Ангина",
      "file": "tonsillitis.md"
    },
    {
      "title": "Отит",
      "file": "otitis.md"
    },
    {
      "title": "Менингит",
      "file": "meningitis.md"
    },
    {
      "title": "Краснуха",
      "file": "rubella.md"
    },
    {
      "title": "Бешенство",
      "file": "rabies.md"
    },
    {
      "title": "Инфекционные болезни",
      "file": "infectious_diseases.md"
    },
    {
      "title": "Вирусные заболевания",
      "file": "viral_diseases.md"
    },
    {
      "title": "Бактериальные инфекции",
      "file": "bacterial_infections.md"
    },
    {
      "title": "Грибковые заболевания",
      "file": "fungal_diseases.md"
    },
    {
      "title": "Паразитарные болезни",
      "file": "parasitic_diseases.md"
    },
    {
      "title": "Генетические заболевания",
      "file": "genetic_diseases.md"
    },
    {
      "title": "Иммунные заболевания",
      "file": "immune_diseases.md"
    },
    {
      "title": "Хронические болезни",
      "file": "chronic_diseases.md"
    },
    {
      "title": "Аллергия",
      "file": "allergies.md"
    },
    {
      "title": "Аутоиммунные заболевания",
      "file": "autoimmune_diseases.md"
    },
    {
      "title": "Грипп",
      "file": "gripp.md"
    }
  ]
}
